mcpsquared_base/__init__.py
mcpsquared_base/base_mcpsquared_agent.py
mcpsquared_base/base_orchestrator.py
mcpsquared_base/chain_selection_mcp_server.py
mcpsquared_base/setup.py
mcpsquared_base/models/__init__.py
mcpsquared_base/models/requests.py
mcpsquared_base/models/schemas.py
mcpsquared_base/tools/__init__.py
mcpsquared_base/tools/chain_selection.py
mcpsquared_base/utils/__init__.py
mcpsquared_base/utils/agent_loader.py
mcpsquared_base/utils/agent_runner.py
mcpsquared_base/utils/workflow_runner.py
mcpsquared_base-0.1.5.dist-info/METADATA
mcpsquared_base-0.1.5.dist-info/WHEEL
mcpsquared_base-0.1.5.dist-info/entry_points.txt
mcpsquared_base-0.1.5.dist-info/top_level.txt
mcpsquared_base-0.1.5.dist-info/RECORD
