Metadata-Version: 2.4
Name: mcpsquared-base
Version: 0.1.5
Summary: Base package for MCPSquared - provides universal loaders/runners and chain selection MCP server
Project-URL: Homepage, https://github.com/sancovp/mcpsquared-base
Project-URL: Repository, https://github.com/sancovp/mcpsquared-base.git
Classifier: Development Status :: 3 - Alpha
Classifier: Intended Audience :: Developers
Classifier: License :: OSI Approved :: MIT License
Classifier: Programming Language :: Python :: 3
Classifier: Programming Language :: Python :: 3.8
Classifier: Programming Language :: Python :: 3.9
Classifier: Programming Language :: Python :: 3.10
Classifier: Programming Language :: Python :: 3.11
Classifier: Programming Language :: Python :: 3.12
Requires-Python: >=3.8
Requires-Dist: mcp-use
Requires-Dist: langchain-openai
Requires-Dist: fastmcp
Dynamic: requires-python
